optimal_congress/__init__.py
optimal_congress/cli.py
optimal_congress/config.py
optimal_congress/io/api.py
optimal_congress/io/cache.py
optimal_congress/optimize.py
optimal_congress/ratings.py
optimal_congress/schema.py
optimal_congress-1.2.0.dist-info/LICENSE
optimal_congress-1.2.0.dist-info/METADATA
optimal_congress-1.2.0.dist-info/WHEEL
optimal_congress-1.2.0.dist-info/entry_points.txt
optimal_congress-1.2.0.dist-info/RECORD
