Metadata-Version: 2.1
Name: optimal-congress
Version: 1.2.0
Summary: CLI to find an optimal, personal schedule for the 38c3 congress.
Home-page: https://github.com/top-on/optimal-congress
Author: top-on
Author-email: top-on@posteo.de
Requires-Python: >=3.11,<4.0
Classifier: Programming Language :: Python :: 3
Classifier: Programming Language :: Python :: 3.11
Classifier: Programming Language :: Python :: 3.12
Requires-Dist: pandas (>=2.2.3,<3.0.0)
Requires-Dist: pandera (>=0.21.1,<0.22.0)
Requires-Dist: pulp (>=2.9.0,<3.0.0)
Requires-Dist: pydantic (>=2.10.3,<3.0.0)
Requires-Dist: pytz (>=2024.2,<2025.0)
Requires-Dist: requests (>=2.32.3,<3.0.0)
Requires-Dist: typer[all] (>=0.15.1,<0.16.0)
